MANIFEST.in
README.rst
callerframe.py
flake8.ini
pylint.ini
setup.py
tox.ini
callerframe.egg-info/PKG-INFO
callerframe.egg-info/SOURCES.txt
callerframe.egg-info/dependency_links.txt
callerframe.egg-info/top_level.txt
docs/Makefile
docs/source/.index.rst.swp
docs/source/conf.py
docs/source/index.rst
docs/source/macros.txt
docs/source/__pycache__/conf.cpython-34.pyc
docs/source/reference/callerframe.rst
docs/source/reference/modules.rst
requirements/docs.txt
requirements/flake8.txt
requirements/install.txt
requirements/pylint.txt
requirements/tests.txt