Metadata-Version: 1.1
Name: callerframe
Version: 1.0.3
Summary: Python library for configuration data
Home-page: https://github.com/simone-campagna/callerframe
Author: Simone Campagna
Author-email: simone.campagna11@gmail.com
License: UNKNOWN
Download-URL: https://github.com/simone-campagna/callerframe/archive/1.0.3.tar.gz
Keywords: decorator caller frame
Platform: UNKNOWN
Classifier: Development Status :: 3 - Alpha
Classifier: Intended Audience :: Developers
Classifier: Topic :: Software Development :: Build Tools
Classifier: License :: OSI Approved :: Apple Public Source License
Classifier: Programming Language :: Python :: 3.4
Classifier: Programming Language :: Python :: 2.7
